{"initial_state": {"id": "8oTfmIADsvGdfMRkWw87-1", "incoming_transitions": [], "label": "Start", "outgoing_transitions": [{"from_state": {"py/id": 1}, "id": "8oTfmIADsvGdfMRkWw87-29", "label": "", "py/object": "model.alts.Transition", "to_state": {"id": "8oTfmIADsvGdfMRkWw87-2", "incoming_transitions": [{"py/id": 4}], "label": "Visit the website", "outgoing_transitions": [{"from_state": {"py/id": 5}, "id": "8oTfmIADsvGdfMRkWw87-30", "label": "", "py/object": "model.alts.Transition", "to_state": {"id": "8oTfmIADsvGdfMRkWw87-4", "incoming_transitions": [{"py/id": 8}], "label": "Decide an item to buy", "outgoing_transitions": [{"from_state": {"py/id": 9}, "id": "8oTfmIADsvGdfMRkWw87-31", "label": "", "py/object": "model.alts.Transition", "to_state": {"id": "8oTfmIADsvGdfMRkWw87-3", "incoming_transitions": [{"py/id": 12}], "label": "Browse or search item", "outgoing_transitions": [{"from_state": {"py/id": 13}, "id": "8oTfmIADsvGdfMRkWw87-32", "label": "", "py/object": "model.alts.Transition", "to_state": {"id": "8oTfmIADsvGdfMRkWw87-6", "incoming_transitions": [{"py/id": 16}], "label": "Search item", "outgoing_transitions": [{"from_state": {"py/id": 17}, "id": "8oTfmIADsvGdfMRkWw87-37", "label": "", "py/object": "model.alts.Transition", "to_state": {"id": "8oTfmIADsvGdfMRkWw87-7", "incoming_transitions": [{"from_state": {"id": "8oTfmIADsvGdfMRkWw87-5", "incoming_transitions": [{"from_state": {"py/id": 13}, "id": "8oTfmIADsvGdfMRkWw87-33", "label": "", "py/object": "model.alts.Transition", "to_state": {"py/id": 24}, "transition_type": "step"}], "label": "Browse item", "outgoing_transitions": [{"py/id": 23}], "py/object": "model.alts.State"}, "id": "8oTfmIADsvGdfMRkWw87-36", "label": "", "py/object": "model.alts.Transition", "to_state": {"py/id": 21}, "transition_type": "step"}, {"py/id": 20}], "label": "Find item", "outgoing_transitions": [{"from_state": {"py/id": 21}, "id": "8oTfmIADsvGdfMRkWw87-38", "label": "", "py/object": "model.alts.Transition", "to_state": {"id": "8oTfmIADsvGdfMRkWw87-8", "incoming_transitions": [{"py/id": 29}], "label": "Found desired item or not", "outgoing_transitions": [{"from_state": {"py/id": 30}, "id": "8oTfmIADsvGdfMRkWw87-39", "label": "", "py/object": "model.alts.Transition", "to_state": {"id": "8oTfmIADsvGdfMRkWw87-9", "incoming_transitions": [{"py/id": 33}], "label": "View item", "outgoing_transitions": [{"from_state": {"py/id": 34}, "id": "8oTfmIADsvGdfMRkWw87-42", "label": "", "py/object": "model.alts.Transition", "to_state": {"id": "8oTfmIADsvGdfMRkWw87-10", "incoming_transitions": [{"py/id": 37}], "label": "Add to cart", "outgoing_transitions": [{"from_state": {"py/id": 38}, "id": "8oTfmIADsvGdfMRkWw87-43", "label": "", "py/object": "model.alts.Transition", "to_state": {"id": "8oTfmIADsvGdfMRkWw87-12", "incoming_transitions": [{"py/id": 41}], "label": "Proceed to payment", "outgoing_transitions": [{"from_state": {"py/id": 42}, "id": "8oTfmIADsvGdfMRkWw87-44", "label": "", "py/object": "model.alts.Transition", "to_state": {"id": "8oTfmIADsvGdfMRkWw87-13", "incoming_transitions": [{"py/id": 45}], "label": "Cancelling payment", "outgoing_transitions": [{"from_state": {"py/id": 46}, "id": "8oTfmIADsvGdfMRkWw87-45", "label": "", "py/object": "model.alts.Transition", "to_state": {"id": "8oTfmIADsvGdfMRkWw87-23", "incoming_transitions": [{"py/id": 49}], "label": "Write feedback to website", "outgoing_transitions": [{"from_state": {"py/id": 50}, "id": "8oTfmIADsvGdfMRkWw87-47", "label": "", "py/object": "model.alts.Transition", "to_state": {"id": "8oTfmIADsvGdfMRkWw87-24", "incoming_transitions": [{"py/id": 53}], "label": "Write feedback", "outgoing_transitions": [{"from_state": {"py/id": 54}, "id": "8oTfmIADsvGdfMRkWw87-49", "label": "", "py/object": "model.alts.Transition", "to_state": {"id": "8oTfmIADsvGdfMRkWw87-26", "incoming_transitions": [{"py/id": 57}], "label": "Submit feedback", "outgoing_transitions": [{"from_state": {"py/id": 58}, "id": "8oTfmIADsvGdfMRkWw87-63", "label": "", "py/object": "model.alts.Transition", "to_state": {"id": "8oTfmIADsvGdfMRkWw87-27", "incoming_transitions": [{"from_state": {"id": "8oTfmIADsvGdfMRkWw87-11", "incoming_transitions": [{"from_state": {"py/id": 30}, "id": "8oTfmIADsvGdfMRkWw87-40", "label": "", "py/object": "model.alts.Transition", "to_state": {"py/id": 65}, "transition_type": "step"}], "label": "Try another time", "outgoing_transitions": [{"py/id": 64}], "py/object": "model.alts.State"}, "id": "8oTfmIADsvGdfMRkWw87-64", "label": "", "py/object": "model.alts.Transition", "to_state": {"py/id": 62}, "transition_type": "step"}, {"from_state": {"id": "8oTfmIADsvGdfMRkWw87-22", "incoming_transitions": [{"from_state": {"id": "8oTfmIADsvGdfMRkWw87-21", "incoming_transitions": [{"from_state": {"id": "8oTfmIADsvGdfMRkWw87-20", "incoming_transitions": [{"from_state": {"id": "8oTfmIADsvGdfMRkWw87-19", "incoming_transitions": [{"from_state": {"id": "8oTfmIADsvGdfMRkWw87-16", "incoming_transitions": [{"from_state": {"id": "8oTfmIADsvGdfMRkWw87-15", "incoming_transitions": [{"from_state": {"id": "8oTfmIADsvGdfMRkWw87-14", "incoming_transitions": [{"from_state": {"py/id": 42}, "id": "8oTfmIADsvGdfMRkWw87-50", "label": "", "py/object": "model.alts.Transition", "to_state": {"py/id": 88}, "transition_type": "step"}], "label": "Via internet banking", "outgoing_transitions": [{"py/id": 87}], "py/object": "model.alts.State"}, "id": "8oTfmIADsvGdfMRkWw87-51", "label": "", "py/object": "model.alts.Transition", "to_state": {"py/id": 85}, "transition_type": "step"}], "label": "Enter your banking credentials", "outgoing_transitions": [{"py/id": 84}], "py/object": "model.alts.State"}, "id": "8oTfmIADsvGdfMRkWw87-52", "label": "", "py/object": "model.alts.Transition", "to_state": {"py/id": 82}, "transition_type": "step"}], "label": "Enter your address", "outgoing_transitions": [{"py/id": 81}], "py/object": "model.alts.State"}, "id": "8oTfmIADsvGdfMRkWw87-53", "label": "", "py/object": "model.alts.Transition", "to_state": {"py/id": 79}, "transition_type": "step"}], "label": "Checkout", "outgoing_transitions": [{"py/id": 78}], "py/object": "model.alts.State"}, "id": "8oTfmIADsvGdfMRkWw87-54", "label": "", "py/object": "model.alts.Transition", "to_state": {"py/id": 76}, "transition_type": "step"}], "label": "Display confirmation page", "outgoing_transitions": [{"py/id": 75}], "py/object": "model.alts.State"}, "id": "8oTfmIADsvGdfMRkWw87-55", "label": "", "py/object": "model.alts.Transition", "to_state": {"py/id": 73}, "transition_type": "step"}], "label": "Print or save page", "outgoing_transitions": [{"py/id": 72}], "py/object": "model.alts.State"}, "id": "8oTfmIADsvGdfMRkWw87-56", "label": "", "py/object": "model.alts.Transition", "to_state": {"py/id": 70}, "transition_type": "step"}], "label": "Display thank you message", "outgoing_transitions": [{"py/id": 69}], "py/object": "model.alts.State"}, "id": "8oTfmIADsvGdfMRkWw87-57", "label": "", "py/object": "model.alts.Transition", "to_state": {"py/id": 62}, "transition_type": "step"}, {"from_state": {"id": "8oTfmIADsvGdfMRkWw87-25", "incoming_transitions": [{"from_state": {"py/id": 50}, "id": "8oTfmIADsvGdfMRkWw87-48", "label": "", "py/object": "model.alts.Transition", "to_state": {"py/id": 99}, "transition_type": "step"}], "label": "Display visit again message", "outgoing_transitions": [{"py/id": 98}], "py/object": "model.alts.State"}, "id": "8oTfmIADsvGdfMRkWw87-62", "label": "", "py/object": "model.alts.Transition", "to_state": {"py/id": 62}, "transition_type": "step"}, {"py/id": 61}], "label": "Exit the website", "outgoing_transitions": [{"from_state": {"py/id": 62}, "id": "8oTfmIADsvGdfMRkWw87-61", "label": "", "py/object": "model.alts.Transition", "to_state": {"id": "8oTfmIADsvGdfMRkWw87-28", "incoming_transitions": [{"py/id": 104}], "label": "End", "outgoing_transitions": [], "py/object": "model.alts.State"}, "transition_type": "step"}], "py/object": "model.alts.State"}, "transition_type": "step"}], "py/object": "model.alts.State"}, "transition_type": "step"}], "py/object": "model.alts.State"}, "transition_type": "step"}, {"py/id": 101}], "py/object": "model.alts.State"}, "transition_type": "step"}], "py/object": "model.alts.State"}, "transition_type": "step"}, {"py/id": 90}], "py/object": "model.alts.State"}, "transition_type": "step"}], "py/object": "model.alts.State"}, "transition_type": "step"}], "py/object": "model.alts.State"}, "transition_type": "step"}, {"py/id": 67}], "py/object": "model.alts.State"}, "transition_type": "step"}], "py/object": "model.alts.State"}, "transition_type": "step"}], "py/object": "model.alts.State"}, "transition_type": "step"}, {"py/id": 26}], "py/object": "model.alts.State"}, "transition_type": "step"}], "py/object": "model.alts.State"}, "transition_type": "step"}], "py/object": "model.alts.State"}, "transition_type": "step"}], "py/object": "model.alts.State"}, "name": "ATMSample", "py/object": "model.alts.ALTS", "states": {"8oTfmIADsvGdfMRkWw87-1": {"py/id": 1}, "8oTfmIADsvGdfMRkWw87-10": {"py/id": 38}, "8oTfmIADsvGdfMRkWw87-11": {"py/id": 65}, "8oTfmIADsvGdfMRkWw87-12": {"py/id": 42}, "8oTfmIADsvGdfMRkWw87-13": {"py/id": 46}, "8oTfmIADsvGdfMRkWw87-14": {"py/id": 88}, "8oTfmIADsvGdfMRkWw87-15": {"py/id": 85}, "8oTfmIADsvGdfMRkWw87-16": {"py/id": 82}, "8oTfmIADsvGdfMRkWw87-19": {"py/id": 79}, "8oTfmIADsvGdfMRkWw87-2": {"py/id": 5}, "8oTfmIADsvGdfMRkWw87-20": {"py/id": 76}, "8oTfmIADsvGdfMRkWw87-21": {"py/id": 73}, "8oTfmIADsvGdfMRkWw87-22": {"py/id": 70}, "8oTfmIADsvGdfMRkWw87-23": {"py/id": 50}, "8oTfmIADsvGdfMRkWw87-24": {"py/id": 54}, "8oTfmIADsvGdfMRkWw87-25": {"py/id": 99}, "8oTfmIADsvGdfMRkWw87-26": {"py/id": 58}, "8oTfmIADsvGdfMRkWw87-27": {"py/id": 62}, "8oTfmIADsvGdfMRkWw87-28": {"py/id": 105}, "8oTfmIADsvGdfMRkWw87-3": {"py/id": 13}, "8oTfmIADsvGdfMRkWw87-4": {"py/id": 9}, "8oTfmIADsvGdfMRkWw87-5": {"py/id": 24}, "8oTfmIADsvGdfMRkWw87-6": {"py/id": 17}, "8oTfmIADsvGdfMRkWw87-7": {"py/id": 21}, "8oTfmIADsvGdfMRkWw87-8": {"py/id": 30}, "8oTfmIADsvGdfMRkWw87-9": {"py/id": 34}}, "transitions": {"Add to cart -> (step)  -> Proceed to payment": {"py/id": 41}, "Browse item -> (step)  -> Find item": {"py/id": 23}, "Browse or search item -> (step)  -> Browse item": {"py/id": 26}, "Browse or search item -> (step)  -> Search item": {"py/id": 16}, "Cancelling payment -> (step)  -> Write feedback to website": {"py/id": 49}, "Checkout -> (step)  -> Display confirmation page": {"py/id": 78}, "Decide an item to buy -> (step)  -> Browse or search item": {"py/id": 12}, "Display confirmation page -> (step)  -> Print or save page": {"py/id": 75}, "Display thank you message -> (step)  -> Exit the website": {"py/id": 69}, "Display visit again message -> (step)  -> Exit the website": {"py/id": 98}, "Enter your address -> (step)  -> Checkout": {"py/id": 81}, "Enter your banking credentials -> (step)  -> Enter your address": {"py/id": 84}, "Exit the website -> (step)  -> End": {"py/id": 104}, "Find item -> (step)  -> Found desired item or not": {"py/id": 29}, "Found desired item or not -> (step)  -> Try another time": {"py/id": 67}, "Found desired item or not -> (step)  -> View item": {"py/id": 33}, "Print or save page -> (step)  -> Display thank you message": {"py/id": 72}, "Proceed to payment -> (step)  -> Cancelling payment": {"py/id": 45}, "Proceed to payment -> (step)  -> Via internet banking": {"py/id": 90}, "Search item -> (step)  -> Find item": {"py/id": 20}, "Start -> (step)  -> Visit the website": {"py/id": 4}, "Submit feedback -> (step)  -> Exit the website": {"py/id": 61}, "Try another time -> (step)  -> Exit the website": {"py/id": 64}, "Via internet banking -> (step)  -> Enter your banking credentials": {"py/id": 87}, "View item -> (step)  -> Add to cart": {"py/id": 37}, "Visit the website -> (step)  -> Decide an item to buy": {"py/id": 8}, "Write feedback -> (step)  -> Submit feedback": {"py/id": 57}, "Write feedback to website -> (step)  -> Display visit again message": {"py/id": 101}, "Write feedback to website -> (step)  -> Write feedback": {"py/id": 53}}}