{
  "data": [
    {
      "data": [],
      "name": [
        {
          "from_state": {
            "id": "QOX-QOyRL-U3UBkbFy3--5",
            "incoming_transitions": [],
            "label": "",
            "outgoing_transitions": [
              {
                "py/id": 5
              }
            ],
            "py/object": "model.alts.State"
          },
          "id": "QOX-QOyRL-U3UBkbFy3--8",
          "label": "",
          "py/object": "model.alts.Transition",
          "to_state": {
            "id": "QOX-QOyRL-U3UBkbFy3--7",
            "incoming_transitions": [
              {
                "py/id": 5
              }
            ],
            "label": "Input Number",
            "outgoing_transitions": [
              {
                "from_state": {
                  "py/id": 9
                },
                "id": "zZ7NoIVB4Zub_XLmL1w5-1",
                "label": "",
                "py/object": "model.alts.Transition",
                "to_state": {
                  "id": "QOX-QOyRL-U3UBkbFy3--9",
                  "incoming_transitions": [
                    {
                      "py/id": 12
                    }
                  ],
                  "label": "Assigning Gap Equal to Total Element in Input Number&nbsp;",
                  "outgoing_transitions": [
                    {
                      "from_state": {
                        "py/id": 13
                      },
                      "id": "QOX-QOyRL-U3UBkbFy3--21",
                      "label": "",
                      "py/object": "model.alts.Transition",
                      "to_state": {
                        "id": "QOX-QOyRL-U3UBkbFy3--20",
                        "incoming_transitions": [
                          {
                            "py/id": 16
                          },
                          {
                            "from_state": {
                              "id": "Pv9dX6mfEltd3Opco7GE-20",
                              "incoming_transitions": [
                                {
                                  "from_state": {
                                    "id": "Pv9dX6mfEltd3Opco7GE-14",
                                    "incoming_transitions": [
                                      {
                                        "from_state": {
                                          "id": "Pv9dX6mfEltd3Opco7GE-6",
                                          "incoming_transitions": [
                                            {
                                              "from_state": {
                                                "py/id": 17
                                              },
                                              "id": "Pv9dX6mfEltd3Opco7GE-7",
                                              "label": "",
                                              "py/object": "model.alts.Transition",
                                              "to_state": {
                                                "py/id": 26
                                              },
                                              "transition_type": "step"
                                            }
                                          ],
                                          "label": "Assgining Pointer to First Element",
                                          "outgoing_transitions": [
                                            {
                                              "py/id": 25
                                            }
                                          ],
                                          "py/object": "model.alts.State"
                                        },
                                        "id": "Nh1D3I1_ObbzlYBHciTE-1",
                                        "label": "",
                                        "py/object": "model.alts.Transition",
                                        "to_state": {
                                          "py/id": 23
                                        },
                                        "transition_type": "step"
                                      },
                                      {
                                        "from_state": {
                                          "id": "Pv9dX6mfEltd3Opco7GE-9",
                                          "incoming_transitions": [
                                            {
                                              "from_state": {
                                                "id": "zZ7NoIVB4Zub_XLmL1w5-13",
                                                "incoming_transitions": [
                                                  {
                                                    "from_state": {
                                                      "py/id": 23
                                                    },
                                                    "id": "Nh1D3I1_ObbzlYBHciTE-5",
                                                    "label": "",
                                                    "py/object": "model.alts.Transition",
                                                    "to_state": {
                                                      "py/id": 34
                                                    },
                                                    "transition_type": "step"
                                                  }
                                                ],
                                                "label": "Check If Pointer&nbsp; Element is Less Than Pointer Element After Gap",
                                                "outgoing_transitions": [
                                                  {
                                                    "from_state": {
                                                      "py/id": 34
                                                    },
                                                    "id": "Pv9dX6mfEltd3Opco7GE-10",
                                                    "label": "",
                                                    "py/object": "model.alts.Transition",
                                                    "to_state": {
                                                      "id": "Pv9dX6mfEltd3Opco7GE-8",
                                                      "incoming_transitions": [
                                                        {
                                                          "py/id": 38
                                                        }
                                                      ],
                                                      "label": "Swap Pointer Element With Pointer Element After Gap",
                                                      "outgoing_transitions": [
                                                        {
                                                          "from_state": {
                                                            "py/id": 39
                                                          },
                                                          "id": "Pv9dX6mfEltd3Opco7GE-11",
                                                          "label": "",
                                                          "py/object": "model.alts.Transition",
                                                          "to_state": {
                                                            "py/id": 31
                                                          },
                                                          "transition_type": "step"
                                                        }
                                                      ],
                                                      "py/object": "model.alts.State"
                                                    },
                                                    "transition_type": "step"
                                                  },
                                                  {
                                                    "py/id": 33
                                                  }
                                                ],
                                                "py/object": "model.alts.State"
                                              },
                                              "id": "Nh1D3I1_ObbzlYBHciTE-9",
                                              "label": "",
                                              "py/object": "model.alts.Transition",
                                              "to_state": {
                                                "py/id": 31
                                              },
                                              "transition_type": "step"
                                            },
                                            {
                                              "py/id": 42
                                            }
                                          ],
                                          "label": "Move Pointer to Next Element",
                                          "outgoing_transitions": [
                                            {
                                              "py/id": 30
                                            }
                                          ],
                                          "py/object": "model.alts.State"
                                        },
                                        "id": "Nh1D3I1_ObbzlYBHciTE-2",
                                        "label": "",
                                        "py/object": "model.alts.Transition",
                                        "to_state": {
                                          "py/id": 23
                                        },
                                        "transition_type": "step"
                                      }
                                    ],
                                    "label": "Check If Pointer&nbsp; Already Passed Last Element",
                                    "outgoing_transitions": [
                                      {
                                        "py/id": 36
                                      },
                                      {
                                        "py/id": 22
                                      }
                                    ],
                                    "py/object": "model.alts.State"
                                  },
                                  "id": "Nh1D3I1_ObbzlYBHciTE-7",
                                  "label": "",
                                  "py/object": "model.alts.Transition",
                                  "to_state": {
                                    "py/id": 20
                                  },
                                  "transition_type": "step"
                                }
                              ],
                              "label": "Check If Swapped Happened This Round Or Gap is Equal to 1",
                              "outgoing_transitions": [
                                {
                                  "from_state": {
                                    "py/id": 20
                                  },
                                  "id": "Pv9dX6mfEltd3Opco7GE-27",
                                  "label": "",
                                  "py/object": "model.alts.Transition",
                                  "to_state": {
                                    "id": "QOX-QOyRL-U3UBkbFy3--37",
                                    "incoming_transitions": [
                                      {
                                        "py/id": 46
                                      }
                                    ],
                                    "label": "Result",
                                    "outgoing_transitions": [
                                      {
                                        "from_state": {
                                          "py/id": 47
                                        },
                                        "id": "QOX-QOyRL-U3UBkbFy3--43",
                                        "label": "",
                                        "py/object": "model.alts.Transition",
                                        "to_state": {
                                          "id": "q8Px36Bj9dSwdPajYqEf-1",
                                          "incoming_transitions": [
                                            {
                                              "py/id": 50
                                            }
                                          ],
                                          "label": "",
                                          "outgoing_transitions": [],
                                          "py/object": "model.alts.State"
                                        },
                                        "transition_type": "step"
                                      }
                                    ],
                                    "py/object": "model.alts.State"
                                  },
                                  "transition_type": "step"
                                },
                                {
                                  "py/id": 19
                                }
                              ],
                              "py/object": "model.alts.State"
                            },
                            "id": "Nh1D3I1_ObbzlYBHciTE-6",
                            "label": "",
                            "py/object": "model.alts.Transition",
                            "to_state": {
                              "py/id": 17
                            },
                            "transition_type": "step"
                          }
                        ],
                        "label": "Assigning Gap With Next Gap Using Shrink Factor",
                        "outgoing_transitions": [
                          {
                            "py/id": 28
                          }
                        ],
                        "py/object": "model.alts.State"
                      },
                      "transition_type": "step"
                    }
                  ],
                  "py/object": "model.alts.State"
                },
                "transition_type": "step"
              }
            ],
            "py/object": "model.alts.State"
          },
          "transition_type": "step"
        },
        {
          "py/id": 12
        },
        {
          "py/id": 16
        },
        {
          "py/id": 28
        },
        {
          "py/id": 25
        },
        {
          "py/id": 36
        },
        {
          "py/id": 38
        },
        {
          "py/id": 42
        },
        {
          "py/id": 30
        },
        {
          "py/id": 36
        },
        {
          "py/id": 33
        },
        {
          "py/id": 30
        }
      ],
      "py/object": "test_generation.test_suite.TestCase",
      "py/seq": []
    },
    {
      "data": [],
      "name": [
        {
          "py/id": 5
        },
        {
          "py/id": 12
        },
        {
          "py/id": 16
        },
        {
          "py/id": 28
        },
        {
          "py/id": 25
        },
        {
          "py/id": 36
        },
        {
          "py/id": 38
        },
        {
          "py/id": 42
        },
        {
          "py/id": 30
        },
        {
          "py/id": 22
        },
        {
          "py/id": 46
        },
        {
          "py/id": 50
        }
      ],
      "py/object": "test_generation.test_suite.TestCase",
      "py/seq": []
    },
    {
      "data": [],
      "name": [
        {
          "py/id": 5
        },
        {
          "py/id": 12
        },
        {
          "py/id": 16
        },
        {
          "py/id": 28
        },
        {
          "py/id": 25
        },
        {
          "py/id": 36
        },
        {
          "py/id": 38
        },
        {
          "py/id": 42
        },
        {
          "py/id": 30
        },
        {
          "py/id": 22
        },
        {
          "py/id": 19
        },
        {
          "py/id": 28
        },
        {
          "py/id": 25
        }
      ],
      "py/object": "test_generation.test_suite.TestCase",
      "py/seq": []
    },
    {
      "data": [],
      "name": [
        {
          "py/id": 5
        },
        {
          "py/id": 12
        },
        {
          "py/id": 16
        },
        {
          "py/id": 28
        },
        {
          "py/id": 25
        },
        {
          "py/id": 36
        },
        {
          "py/id": 33
        },
        {
          "py/id": 30
        },
        {
          "py/id": 36
        },
        {
          "py/id": 38
        },
        {
          "py/id": 42
        },
        {
          "py/id": 30
        }
      ],
      "py/object": "test_generation.test_suite.TestCase",
      "py/seq": []
    },
    {
      "data": [],
      "name": [
        {
          "py/id": 5
        },
        {
          "py/id": 12
        },
        {
          "py/id": 16
        },
        {
          "py/id": 28
        },
        {
          "py/id": 25
        },
        {
          "py/id": 36
        },
        {
          "py/id": 33
        },
        {
          "py/id": 30
        },
        {
          "py/id": 36
        },
        {
          "py/id": 33
        },
        {
          "py/id": 30
        }
      ],
      "py/object": "test_generation.test_suite.TestCase",
      "py/seq": []
    },
    {
      "data": [],
      "name": [
        {
          "py/id": 5
        },
        {
          "py/id": 12
        },
        {
          "py/id": 16
        },
        {
          "py/id": 28
        },
        {
          "py/id": 25
        },
        {
          "py/id": 36
        },
        {
          "py/id": 33
        },
        {
          "py/id": 30
        },
        {
          "py/id": 22
        },
        {
          "py/id": 46
        },
        {
          "py/id": 50
        }
      ],
      "py/object": "test_generation.test_suite.TestCase",
      "py/seq": []
    },
    {
      "data": [],
      "name": [
        {
          "py/id": 5
        },
        {
          "py/id": 12
        },
        {
          "py/id": 16
        },
        {
          "py/id": 28
        },
        {
          "py/id": 25
        },
        {
          "py/id": 36
        },
        {
          "py/id": 33
        },
        {
          "py/id": 30
        },
        {
          "py/id": 22
        },
        {
          "py/id": 19
        },
        {
          "py/id": 28
        },
        {
          "py/id": 25
        }
      ],
      "py/object": "test_generation.test_suite.TestCase",
      "py/seq": []
    },
    {
      "data": [],
      "name": [
        {
          "py/id": 5
        },
        {
          "py/id": 12
        },
        {
          "py/id": 16
        },
        {
          "py/id": 28
        },
        {
          "py/id": 25
        },
        {
          "py/id": 22
        },
        {
          "py/id": 46
        },
        {
          "py/id": 50
        }
      ],
      "py/object": "test_generation.test_suite.TestCase",
      "py/seq": []
    },
    {
      "data": [],
      "name": [
        {
          "py/id": 5
        },
        {
          "py/id": 12
        },
        {
          "py/id": 16
        },
        {
          "py/id": 28
        },
        {
          "py/id": 25
        },
        {
          "py/id": 22
        },
        {
          "py/id": 19
        },
        {
          "py/id": 28
        },
        {
          "py/id": 25
        },
        {
          "py/id": 36
        },
        {
          "py/id": 38
        },
        {
          "py/id": 42
        },
        {
          "py/id": 30
        }
      ],
      "py/object": "test_generation.test_suite.TestCase",
      "py/seq": []
    },
    {
      "data": [],
      "name": [
        {
          "py/id": 5
        },
        {
          "py/id": 12
        },
        {
          "py/id": 16
        },
        {
          "py/id": 28
        },
        {
          "py/id": 25
        },
        {
          "py/id": 22
        },
        {
          "py/id": 19
        },
        {
          "py/id": 28
        },
        {
          "py/id": 25
        },
        {
          "py/id": 36
        },
        {
          "py/id": 33
        },
        {
          "py/id": 30
        }
      ],
      "py/object": "test_generation.test_suite.TestCase",
      "py/seq": []
    },
    {
      "data": [],
      "name": [
        {
          "py/id": 5
        },
        {
          "py/id": 12
        },
        {
          "py/id": 16
        },
        {
          "py/id": 28
        },
        {
          "py/id": 25
        },
        {
          "py/id": 22
        },
        {
          "py/id": 19
        },
        {
          "py/id": 28
        },
        {
          "py/id": 25
        },
        {
          "py/id": 22
        },
        {
          "py/id": 46
        },
        {
          "py/id": 50
        }
      ],
      "py/object": "test_generation.test_suite.TestCase",
      "py/seq": []
    },
    {
      "data": [],
      "name": [
        {
          "py/id": 5
        },
        {
          "py/id": 12
        },
        {
          "py/id": 16
        },
        {
          "py/id": 28
        },
        {
          "py/id": 25
        },
        {
          "py/id": 22
        },
        {
          "py/id": 19
        },
        {
          "py/id": 28
        },
        {
          "py/id": 25
        },
        {
          "py/id": 22
        },
        {
          "py/id": 19
        }
      ],
      "py/object": "test_generation.test_suite.TestCase",
      "py/seq": []
    },
    {
      "data": [],
      "name": [
        {
          "py/id": 5
        },
        {
          "py/id": 12
        },
        {
          "py/id": 16
        },
        {
          "py/id": 28
        },
        {
          "py/id": 25
        },
        {
          "py/id": 36
        },
        {
          "py/id": 38
        },
        {
          "py/id": 42
        },
        {
          "py/id": 30
        },
        {
          "py/id": 36
        },
        {
          "py/id": 38
        },
        {
          "py/id": 42
        },
        {
          "py/id": 30
        }
      ],
      "py/object": "test_generation.test_suite.TestCase",
      "py/seq": []
    }
  ],
  "name": "CombSort",
  "py/object": "test_generation.test_suite.TestSuite",
  "py/seq": [
    {
      "py/id": 2
    },
    {
      "py/id": 55
    },
    {
      "py/id": 58
    },
    {
      "py/id": 61
    },
    {
      "py/id": 64
    },
    {
      "py/id": 67
    },
    {
      "py/id": 70
    },
    {
      "py/id": 73
    },
    {
      "py/id": 76
    },
    {
      "py/id": 79
    },
    {
      "py/id": 82
    },
    {
      "py/id": 85
    },
    {
      "py/id": 88
    }
  ]
}